lifter/__init__.py
lifter/auth.py
lifter/db.py
lifter/hub.py
lifter_hub/__init__.py
lifter_hub/db.py
lifter_hub/hub.py
lifter_hub-0.1.0.dist-info/METADATA
lifter_hub-0.1.0.dist-info/WHEEL
lifter_hub-0.1.0.dist-info/top_level.txt
lifter_hub-0.1.0.dist-info/RECORD
